LICENSE
MANIFEST.in
Makefile
README.md
requirements.txt
setup.cfg
setup.py
test_pycld2.py
LTpycld2.egg-info/PKG-INFO
LTpycld2.egg-info/SOURCES.txt
LTpycld2.egg-info/dependency_links.txt
LTpycld2.egg-info/top_level.txt
bindings/README
bindings/encodings.cc
bindings/gen_enc.py
bindings/gen_test.py
bindings/pycldmodule.cc
bindings/test.py
bindings/test_shuffle.py
cld2/internal/cld2_do_score.cc
cld2/internal/cld2_dynamic_compat.h
cld2/internal/cld2_dynamic_data.cc
cld2/internal/cld2_dynamic_data.h
cld2/internal/cld2_dynamic_data_extractor.cc
cld2/internal/cld2_dynamic_data_extractor.h
cld2/internal/cld2_dynamic_data_loader.cc
cld2/internal/cld2_dynamic_data_loader.h
cld2/internal/cld2_dynamic_data_tool.cc
cld2/internal/cld2_generated_cjk_compatible.cc
cld2/internal/cld2_generated_deltaocta0122.cc
cld2/internal/cld2_generated_deltaocta0527.cc
cld2/internal/cld2_generated_deltaoctachrome.cc
cld2/internal/cld2_generated_deltaoctachrome0122.cc
cld2/internal/cld2_generated_deltaoctachrome0614.cc
cld2/internal/cld2_generated_distinctocta0122.cc
cld2/internal/cld2_generated_distinctocta0527.cc
cld2/internal/cld2_generated_distinctoctachrome.cc
cld2/internal/cld2_generated_distinctoctachrome0122.cc
cld2/internal/cld2_generated_distinctoctachrome0604.cc
cld2/internal/cld2_generated_octa2_dummy.cc
cld2/internal/cld2_generated_quad0122.cc
cld2/internal/cld2_generated_quad0720.cc
cld2/internal/cld2_generated_quadchrome0122_16.cc
cld2/internal/cld2_generated_quadchrome0122_19.cc
cld2/internal/cld2_generated_quadchrome0122_2.cc
cld2/internal/cld2_generated_quadchrome0715.cc
cld2/internal/cld2_generated_quadchrome_16.cc
cld2/internal/cld2_generated_quadchrome_2.cc
cld2/internal/cld2_unittest.cc
cld2/internal/cld2_unittest_full.cc
cld2/internal/cld2tablesummary.h
cld2/internal/cld_generated_cjk_delta_bi_32.cc
cld2/internal/cld_generated_cjk_delta_bi_4.cc
cld2/internal/cld_generated_cjk_uni_prop_80.cc
cld2/internal/cld_generated_score_quad_octa_0122.cc
cld2/internal/cld_generated_score_quad_octa_0122_2.cc
cld2/internal/cld_generated_score_quad_octa_1024_256.cc
cld2/internal/cld_generated_score_quad_octa_2.cc
